cellvoyager_types/__init__.py
cellvoyager_types/_metadata.py
cellvoyager_types/_xarray.py
cellvoyager_types-0.9.1.dist-info/METADATA
cellvoyager_types-0.9.1.dist-info/WHEEL
cellvoyager_types-0.9.1.dist-info/licenses/LICENSE
cellvoyager_types-0.9.1.dist-info/RECORD
